[{"first":[{"id":0,"img":"url(/img/wy_09.png)","val":"美食"},{"id":1,"img":"url(/img/wy_11.png)","val":"超市便利"},{"id":2,"img":"url(/img/wy_13.png)","val":"生鲜果蔬"},{"id":3,"img":"url(/img/wy_15.png)","val":"美团专送"},{"id":4,"img":"url(/img/wy_17.png)","val":"跑腿代购"}],"second":[{"id":5,"img":"url(/img/wy_24.png)","val":"晚餐优选"},{"id":6,"img":"url(/img/wy_25.png)","val":"甜点饮品"},{"id":7,"img":"url(/img/wy_26.png)","val":"快食简餐"},{"id":8,"img":"url(/img/wy_27.png)","val":"精选套餐"},{"id":9,"img":"url(/img/wy_28.png)","val":"医药健康"}]}]